setup.py
dsnd_proba/Binomialdistribution.py
dsnd_proba/Gaussiandistribution.py
dsnd_proba/Generaldistribution.py
dsnd_proba/__init__.py
dsnd_proba.egg-info/PKG-INFO
dsnd_proba.egg-info/SOURCES.txt
dsnd_proba.egg-info/dependency_links.txt
dsnd_proba.egg-info/not-zip-safe
dsnd_proba.egg-info/top_level.txt