Metadata-Version: 1.0
Name: dsnd-proba
Version: 0.1
Summary: Gaussian and Binomial distributions
Home-page: UNKNOWN
Author: Syed Mustaqhim
Author-email: syedmustaqhim777@gmail.com
License: UNKNOWN
Platform: UNKNOWN
